mobiu_q/__init__.py
mobiu_q/catalog.py
mobiu_q/cli.py
mobiu_q/core.py
mobiu_q-1.4.0.dist-info/METADATA
mobiu_q-1.4.0.dist-info/WHEEL
mobiu_q-1.4.0.dist-info/entry_points.txt
mobiu_q-1.4.0.dist-info/top_level.txt
mobiu_q-1.4.0.dist-info/RECORD
