Metadata-Version: 2.4
Name: mobiu-q
Version: 1.4.0
Summary: Soft Algebra Optimizer for Quantum & Complex Optimization
Author-email: Mobiu Technologies <ai@mobiu.ai>
License: Proprietary
Project-URL: Homepage, https://app.mobiu.ai
Project-URL: Documentation, https://pypi.org/project/mobiu-q/
Keywords: quantum,optimization,VQE,QAOA,machine-learning
Classifier: Development Status :: 4 - Beta
Classifier: Intended Audience :: Science/Research
Classifier: Topic :: Scientific/Engineering :: Physics
Classifier: Topic :: Scientific/Engineering :: Artificial Intelligence
Classifier: Programming Language :: Python :: 3
Classifier: Programming Language :: Python :: 3.8
Classifier: Programming Language :: Python :: 3.9
Classifier: Programming Language :: Python :: 3.10
Classifier: Programming Language :: Python :: 3.11
Classifier: Programming Language :: Python :: 3.12
Requires-Python: >=3.8
Requires-Dist: numpy>=1.21.0
Requires-Dist: requests>=2.25.0
Provides-Extra: dev
Requires-Dist: pytest>=7.0; extra == "dev"
Requires-Dist: pytest-cov; extra == "dev"
Provides-Extra: full
Requires-Dist: scipy>=1.7.0; extra == "full"
Requires-Dist: qiskit>=0.40.0; extra == "full"
